{"50":{"hex":"#E0F0E0","contrast":"dark"},"100":{"hex":"#B3D9B3","contrast":"dark"},"200":{"hex":"#80C080","contrast":"dark"},"300":{"hex":"#4DA64D","contrast":"dark"},"400":{"hex":"#269326","contrast":"light"},"500":{"hex":"#008000","contrast":"light"},"600":{"hex":"#007800","contrast":"light"},"700":{"hex":"#006D00","contrast":"light"},"800":{"hex":"#006300","contrast":"light"},"900":{"hex":"#005000","contrast":"light"},"name":"green","A100":{"hex":"#AFFF8C","contrast":"dark"},"A200":{"hex":"#8BFF59","contrast":"dark"},"A400":{"hex":"#67FF26","contrast":"dark"},"A700":{"hex":"#56FF0D","contrast":"dark"}}