{"50":{"hex":"#F0E0E0","contrast":"dark"},"100":{"hex":"#D9B3B3","contrast":"dark"},"200":{"hex":"#C08080","contrast":"dark"},"300":{"hex":"#A64D4D","contrast":"light"},"400":{"hex":"#932626","contrast":"light"},"500":{"hex":"#800000","contrast":"light"},"600":{"hex":"#780000","contrast":"light"},"700":{"hex":"#6D0000","contrast":"light"},"800":{"hex":"#630000","contrast":"light"},"900":{"hex":"#500000","contrast":"light"},"name":"maroon","A100":{"hex":"#FF8CAF","contrast":"dark"},"A200":{"hex":"#FF598B","contrast":"dark"},"A400":{"hex":"#FF2667","contrast":"light"},"A700":{"hex":"#FF0D56","contrast":"light"}}